AUTHORS.rst
CONTRIBUTING.rst
HISTORY.rst
LICENSE
MANIFEST.in
README.rst
setup.cfg
setup.py
bingo/__init__.py
bingo/bingo.py
bingo.egg-info/PKG-INFO
bingo.egg-info/SOURCES.txt
bingo.egg-info/dependency_links.txt
bingo.egg-info/not-zip-safe
bingo.egg-info/top_level.txt