Metadata-Version: 1.1
Name: bingo
Version: 0.1.14
Summary: Bingo is a library that creates bingo cards and game raffles
Home-page: https://github.com/oscarolar/bingo
Author: Oscar Alca
Author-email: oszckar@gmail.com
License: BSD
Keywords: bingo
Platform: UNKNOWN
Classifier: Development Status :: 2 - Pre-Alpha
Classifier: Intended Audience :: Developers
Classifier: License :: OSI Approved :: BSD License
Classifier: Natural Language :: English
Classifier: Programming Language :: Python :: 2
Classifier: Programming Language :: Python :: 2.6
Classifier: Programming Language :: Python :: 2.7
Classifier: Programming Language :: Python :: 3
Classifier: Programming Language :: Python :: 3.3
